pyproject.toml
setup.py
ntcss/__init__.py
ntcss/const.py
ntcss/ntml_parser.py
ntcss/ntmlc.py
ntcss/setup.py
ntcss/tran.py
ntml/__init__.py
ntml/const.py
ntml/ntml_parser.py
ntml/ntmlc.py
ntml/setup.py
ntml/tran.py
pyntweb.egg-info/PKG-INFO
pyntweb.egg-info/SOURCES.txt
pyntweb.egg-info/dependency_links.txt
pyntweb.egg-info/not-zip-safe
pyntweb.egg-info/requires.txt
pyntweb.egg-info/top_level.txt
webfalco/__init__.py
webfalco/const.py
webfalco/lrparser.py
webfalco/setup.py
webfalco/tran.py
webfalco/webfalcoc.py